jalali_calendar/__init__.py
jalali_calendar/jalali_calendar.py
jalali_calendar-1.3.0.dist-info/LICENSE
jalali_calendar-1.3.0.dist-info/METADATA
jalali_calendar-1.3.0.dist-info/WHEEL
jalali_calendar-1.3.0.dist-info/top_level.txt
jalali_calendar-1.3.0.dist-info/RECORD
