Metadata-Version: 2.1
Name: jalali-calendar
Version: 1.3.0
Summary: jalali_calendar allows you to have a calendar with Jalali dates under the terminal.
Home-page: https://github.com/mimseyedi/jalali_calendar
Author: mimseyedi
Author-email: mim.seyedi@gmail.com
License: MIT
Classifier: Programming Language :: Python :: 3
Classifier: Programming Language :: Python :: 3 :: Only
Classifier: Programming Language :: Python :: 3.7
Classifier: Programming Language :: Python :: 3.8
Requires-Python: >=3.7
License-File: LICENSE
